shapley_fda/__init__.py
shapley_fda/shapley_fda_explainer.py
ShapleyFDA-0.0.2.dist-info/LICENSE
ShapleyFDA-0.0.2.dist-info/METADATA
ShapleyFDA-0.0.2.dist-info/WHEEL
ShapleyFDA-0.0.2.dist-info/top_level.txt
ShapleyFDA-0.0.2.dist-info/RECORD
