Metadata-Version: 2.1
Name: ShapleyFDA
Version: 0.0.2
Summary: A python package implementing Shapley FDA value
Author-email: Cristian Pachón García <cc.pachon@gmail.com>
License:                     GNU GENERAL PUBLIC LICENSE
Project-URL: documentation, https://github.com/pachoning/ShapleyFDA
Project-URL: repository, https://github.com/pachoning/ShapleyFDA
Keywords: Interpretable Machine Learning,eXplainalbe Artificial Intelligence,Functional Data Analysis,Machine Learning,Python
Classifier: License :: OSI Approved :: GNU General Public License v3 or later (GPLv3+)
Requires-Python: >=3.8
License-File: LICENSE
Requires-Dist: matplotlib
Requires-Dist: numpy
Provides-Extra: dev
Requires-Dist: black; extra == "dev"
